{
  "items":[
    {
      "event_id":"65",
      "round":"",
      "event_class":"0",
      "event_name":" ",
      "comment":"Dominio di Marc Marquez in queste Libere 4. Il leader del Mondiale mostra un gran passo, rifilando notevoli distacchi. Rossi e' il primo degli ''altri'', davanti ad Aleix Espargaro. A breve scatta il Q1."
    },
    {
      "event_id":"60",
      "round":"",
      "event_class":"12",
      "event_name":"Arrivo",
      "comment":"Sventola la bandiera a scacchi."
    },
    {
      "event_id":"55",
      "round":"",
      "event_class":"0",
      "event_name":" ",
      "comment":"Lieve miglioramento per Lorenzo, che rimane tuttavia piuttosto lontano dalle posizioni che contano."
    },
    {
      "event_id":"50",
      "round":"",
      "event_class":"4",
      "event_name":"Imprevisto",
      "comment":"Scivolata di Eugene Laverty, niente di grave per lui."
    },
    {
      "event_id":"45",
      "round":"",
      "event_class":"0",
      "event_name":" ",
      "comment":"Si migliora, fino alla terza posizione, Aleix Espargaro."
    },
    {
      "event_id":"40",
      "round":"",
      "event_class":"0",
      "event_name":" ",
      "comment":"Resiste il miglior tempo di Marquez, con ampio margine su tutti gli altri piloti."
    },
    {
      "event_id":"35",
      "round":"",
      "event_class":"0",
      "event_name":" ",
      "comment":"E' regolarmente in pista Danilo Petrucci, nonostante il brutto incidente della mattina, quando in uscita dalla corsia box si e' trovato davanti la moto di Pol Espargaro."
    },
    {
      "event_id":"30",
      "round":"",
      "event_class":"0",
      "event_name":" ",
      "comment":"Sale in seconda posizione Valentino Rossi, seppur piuttosto lontano dal miglior tempo di Marquez."
    },
    {
      "event_id":"25",
      "round":"",
      "event_class":"0",
      "event_name":" ",
      "comment":"Che passo di Marquez. Nuovi miglioramenti per il leader della classifica, che pare davvero il pilota piu' in palla in questo weekend."
    },
    {
      "event_id":"20",
      "round":"",
      "event_class":"0",
      "event_name":" ",
      "comment":"Primi tempi validi: c'e' ancora Marquez al comando, davanti al compagno Pedrosa."
    },
    {
      "event_id":"15",
      "round":"",
      "event_class":"0",
      "event_name":" ",
      "comment":"I piloti escono sul circuito."
    },
    {
      "event_id":"10",
      "round":"",
      "event_class":"0",
      "event_name":" ",
      "comment":"In mattinata, miglior tempo di Marc Marquez, poi caduto, cosi' come altri piloti, tra cui Valentino Rossi in apertura di sessione."
    },
    {
      "event_id":"5",
      "round":"",
      "event_class":"0",
      "event_name":" ",
      "comment":"Buongiorno a tutti da Aragon, dove stanno per iniziare le Libere 4."
    }
  ]
}
