{
  "competition_id":"41",
  "competition_name":"CAMPIONATO MOND.LE PISTA",
  "competition_short_name":"MOTOMONDIALE",
  "edition_id":"1087",
  "edition_name":"2009",
  "events":[
    {
      "sequence":1,
      "id":21653,
      "description":"GP Qatar",
      "country_id":"QAT",
      "country":"Qatar",
      "date_start":"13-04-2009",
      "date_start_to_print":"13 Apr 2009",
      "date_end":"13-04-2009",
      "date_end_to_print":"13 Apr 2009",
      "status":"ended",
      "current":"no"
    },
    {
      "sequence":2,
      "id":21668,
      "description":"GP Giappone",
      "country_id":"JPN",
      "country":"Giappone",
      "date_start":"26-04-2009",
      "date_start_to_print":"26 Apr 2009",
      "date_end":"26-04-2009",
      "date_end_to_print":"26 Apr 2009",
      "status":"ended",
      "current":"no"
    },
    {
      "sequence":3,
      "id":21683,
      "description":"GP Spagna",
      "country_id":"ESP",
      "country":"Spagna",
      "date_start":"03-05-2009",
      "date_start_to_print":"03 Mag 2009",
      "date_end":"03-05-2009",
      "date_end_to_print":"03 Mag 2009",
      "status":"ended",
      "current":"no"
    },
    {
      "sequence":4,
      "id":21698,
      "description":"GP Francia",
      "country_id":"FRA",
      "country":"Francia",
      "date_start":"17-05-2009",
      "date_start_to_print":"17 Mag 2009",
      "date_end":"17-05-2009",
      "date_end_to_print":"17 Mag 2009",
      "status":"ended",
      "current":"no"
    },
    {
      "sequence":5,
      "id":21713,
      "description":"GP Italia",
      "country_id":"ITA",
      "country":"Italia",
      "date_start":"31-05-2009",
      "date_start_to_print":"31 Mag 2009",
      "date_end":"31-05-2009",
      "date_end_to_print":"31 Mag 2009",
      "status":"ended",
      "current":"no"
    },
    {
      "sequence":6,
      "id":21728,
      "description":"GP Catalunya",
      "country_id":"ESP",
      "country":"Spagna",
      "date_start":"14-06-2009",
      "date_start_to_print":"14 Giu 2009",
      "date_end":"14-06-2009",
      "date_end_to_print":"14 Giu 2009",
      "status":"ended",
      "current":"no"
    },
    {
      "sequence":7,
      "id":21751,
      "description":"GP Olanda",
      "country_id":"NED",
      "country":"Olanda",
      "date_start":"27-06-2009",
      "date_start_to_print":"27 Giu 2009",
      "date_end":"27-06-2009",
      "date_end_to_print":"27 Giu 2009",
      "status":"ended",
      "current":"no"
    },
    {
      "sequence":8,
      "id":21755,
      "description":"GP Stati Uniti",
      "country_id":"USA",
      "country":"Stati Uniti",
      "date_start":"05-07-2009",
      "date_start_to_print":"05 Lug 2009",
      "date_end":"05-07-2009",
      "date_end_to_print":"05 Lug 2009",
      "status":"ended",
      "current":"no"
    },
    {
      "sequence":9,
      "id":21767,
      "description":"GP Germania",
      "country_id":"GER",
      "country":"Germania",
      "date_start":"19-07-2009",
      "date_start_to_print":"19 Lug 2009",
      "date_end":"19-07-2009",
      "date_end_to_print":"19 Lug 2009",
      "status":"ended",
      "current":"no"
    },
    {
      "sequence":10,
      "id":21779,
      "description":"GP Gran Bretagna",
      "country_id":"GBR",
      "country":"Gran Bretagna",
      "date_start":"26-07-2009",
      "date_start_to_print":"26 Lug 2009",
      "date_end":"26-07-2009",
      "date_end_to_print":"26 Lug 2009",
      "status":"ended",
      "current":"no"
    },
    {
      "sequence":11,
      "id":21791,
      "description":"GP Repubblica Ceca",
      "country_id":"CZE",
      "country":"Rep. Ceca",
      "date_start":"16-08-2009",
      "date_start_to_print":"16 Ago 2009",
      "date_end":"16-08-2009",
      "date_end_to_print":"16 Ago 2009",
      "status":"ended",
      "current":"no"
    },
    {
      "sequence":12,
      "id":21803,
      "description":"GP Indianapolis",
      "country_id":"USA",
      "country":"Stati Uniti",
      "date_start":"30-08-2009",
      "date_start_to_print":"30 Ago 2009",
      "date_end":"30-08-2009",
      "date_end_to_print":"30 Ago 2009",
      "status":"ended",
      "current":"no"
    },
    {
      "sequence":13,
      "id":21815,
      "description":"GP San Marino",
      "country_id":"SMR",
      "country":"San Marino",
      "date_start":"06-09-2009",
      "date_start_to_print":"06 Set 2009",
      "date_end":"06-09-2009",
      "date_end_to_print":"06 Set 2009",
      "status":"ended",
      "current":"no"
    },
    {
      "sequence":14,
      "id":21840,
      "description":"GP Portogallo",
      "country_id":"POR",
      "country":"Portogallo",
      "date_start":"04-10-2009",
      "date_start_to_print":"04 Ott 2009",
      "date_end":"04-10-2009",
      "date_end_to_print":"04 Ott 2009",
      "status":"ended",
      "current":"no"
    },
    {
      "sequence":15,
      "id":21851,
      "description":"GP Australia",
      "country_id":"AUS",
      "country":"Australia",
      "date_start":"18-10-2009",
      "date_start_to_print":"18 Ott 2009",
      "date_end":"18-10-2009",
      "date_end_to_print":"18 Ott 2009",
      "status":"ended",
      "current":"no"
    },
    {
      "sequence":16,
      "id":21863,
      "description":"GP Malesia",
      "country_id":"MAS",
      "country":"Malesia",
      "date_start":"25-10-2009",
      "date_start_to_print":"25 Ott 2009",
      "date_end":"25-10-2009",
      "date_end_to_print":"25 Ott 2009",
      "status":"ended",
      "current":"no"
    },
    {
      "sequence":17,
      "id":21816,
      "description":"GP Comunita' Valenciana",
      "country_id":"ESP",
      "country":"Spagna",
      "date_start":"08-11-2009",
      "date_start_to_print":"08 Nov 2009",
      "date_end":"08-11-2009",
      "date_end_to_print":"08 Nov 2009",
      "status":"ended",
      "current":"yes"
    }
  ]
}
